molpipx/__init__.py
molpipx/load_pip.py
molpipx/pip_anisotropic_flax.py
molpipx/pip_flax.py
molpipx/pip_generator.py
molpipx/pipgp_flax.py
molpipx/pipnn_flax.py
molpipx/trainig_anisotropic_model.py
molpipx/training_linear_model.py
molpipx/utils.py
molpipx/utils_gradients.py
molpipx/utils_training.py
molpipx/data/__init__.py
molpipx/data/loader.py
molpipx/data/Acetaldehyde/Acetaldehyde_singlet.xyz
molpipx/data/CH2O/load_data_CH2O.py
molpipx/data/CH2O/monomials_2_1_1_6.py
molpipx/data/CH2O/polynomials_2_1_1_6.py
molpipx/data/CH2O/regions_datasets_only_energies/01_min.xyz
molpipx/data/CH2O/regions_datasets_only_energies/02_cis.xyz
molpipx/data/CH2O/regions_datasets_only_energies/03_trans.xyz
molpipx/data/DDEthanol/Test_Energy_data.xyz
molpipx/data/DDEthanol/Train_data_50000.xyz
molpipx/data/DDEthanol/load_data_ddethanol.py
molpipx/data/DDEthanol/PIP_deg_2/monomials_ddethanol_p2.py
molpipx/data/DDEthanol/PIP_deg_2/polynomials_ddethanol_p2.py
molpipx/data/Ethanol/Ethanol.xyz
molpipx/data/Ethanol/main.py
molpipx/data/Methane/Methane.xyz
molpipx/data/Methane/PIP_deg_3/monomials_deg_3.py
molpipx/data/Methane/PIP_deg_3/polynomials_deg_3.py
molpipx/data/Methane/PIP_deg_4/monomials_deg_4.py
molpipx/data/Methane/PIP_deg_4/polynomials_deg_4.py
molpipx/data/Methane/PIP_deg_5/monomials_deg_5.py
molpipx/data/Methane/PIP_deg_5/polynomials_deg_5.py
molpipx/data/Methane/PIP_deg_6/monomials_deg_6.py
molpipx/data/Methane/PIP_deg_6/polynomials_deg_6.py
molpipx/msa_files/__init__.py
molpipx/msa_files/molecule_A2B/__init__.py
molpipx/msa_files/molecule_A2B/monomials_MOL_2_1_3.py
molpipx/msa_files/molecule_A2B/monomials_MOL_2_1_4.py
molpipx/msa_files/molecule_A2B/monomials_MOL_2_1_5.py
molpipx/msa_files/molecule_A2B/monomials_MOL_2_1_6.py
molpipx/msa_files/molecule_A2B/monomials_MOL_2_1_7.py
molpipx/msa_files/molecule_A2B/monomials_MOL_2_1_8.py
molpipx/msa_files/molecule_A2B/msa_2_1_files.zip
molpipx/msa_files/molecule_A2B/polynomials_MOL_2_1_3.py
molpipx-0.1.dist-info/licenses/LICENSE-APACHE
molpipx-0.1.dist-info/licenses/LICENSE-MIT
molpipx-0.1.dist-info/METADATA
molpipx-0.1.dist-info/WHEEL
molpipx-0.1.dist-info/top_level.txt
molpipx-0.1.dist-info/RECORD
