Metadata-Version: 2.4
Name: molpipx
Version: 0.1
Summary: MOLPIPx: Permutationally Invariant Polynomials in JAX
Requires-Python: >=3.10
License-File: LICENSE-APACHE
License-File: LICENSE-MIT
Requires-Dist: jax
Requires-Dist: flax
Requires-Dist: optax
Requires-Dist: chex<1.0.0
Requires-Dist: jaxtyping
Requires-Dist: numpy
Requires-Dist: scipy
Requires-Dist: gpjax
Dynamic: license-file
Dynamic: requires-python
